superprikol.py
superprikol-1.1.dist-info/WHEEL
superprikol-1.1.dist-info/METADATA
superprikol-1.1.dist-info/RECORD
