Metadata-Version: 2.1
Name: superprikol
Version: 1.1
Summary: Prikol rzhaka klass
Author: TheBruk
Author-email: no.point2007@gmail.com
Requires-Python: >=3.6,<4.0
Classifier: Programming Language :: Python :: 3
Classifier: Programming Language :: Python :: 3.10
Classifier: Programming Language :: Python :: 3.6
Classifier: Programming Language :: Python :: 3.7
Classifier: Programming Language :: Python :: 3.8
Classifier: Programming Language :: Python :: 3.9
